pydependance/__init__.py
pydependance/__main__.py
pydependance/_core.py
pydependance-0.1.0.dist-info/LICENSE
pydependance-0.1.0.dist-info/METADATA
pydependance-0.1.0.dist-info/WHEEL
pydependance-0.1.0.dist-info/top_level.txt
pydependance-0.1.0.dist-info/RECORD
