Metadata-Version: 2.1
Name: pydependance
Version: 0.1.0
Summary: Python local package dependency discovery and resolution
Home-page: https://github.com/nmichlo/pydependance
Author: Nathan Juraj Michlo
Author-email: NathanJMichlo@gmail.com
Classifier: License :: OSI Approved :: MIT License
Classifier: Operating System :: OS Independent
Classifier: Programming Language :: Python :: 3.10
Requires-Python: >=3.10
License-File: LICENSE
Requires-Dist: pip (>=21.0)
